Workbook

Sheet Income Statement
A1: LULULEMON ATHLETICA INC.
A2: Pro Forma Income Statement ($ in millions)
A3: Source: Bloomberg Terminal
B5: FY2023A | C5: FY2024A | D5: FY2025A | E5: FY2026E | F5: FY2027E | G5: FY2028E
A6: Net Revenue | B6: 8110.518 | C6: 9619.278 | D6: 10588.126 | E6: 11040.29 | F6: 11537.65 | G6: 12190.48
A7: YoY Growth % | B7: 0.296 | C7: 0.186 | D7: 0.101 | E7: 0.043 | F7: 0.045 | G7: 0.057
A9: Cost of Goods Sold | B9: 3618.178 | C9: 4009.873 | D9: 4317.315 | E9: =B6*(1-0.566) | F9: =C6*(1-0.551) | G9: =D6*(1-0.555)
A10: Gross Profit | B10: 4492.34 | C10: 5609.405 | D10: 6270.811 | E10: 6242.51 | F10: 6361.63 | G10: 6762.06
A11: Gross Margin % | B11: 0.554 | C11: 0.583 | D11: 0.592 | E11: 0.566 | F11: 0.551 | G11: 0.555
A13: Selling, General & Admin | B13: 2757.447 | C13: 3397.218 | D13: 3762.379 | E13: =E6*0.355 | F13: =F6*0.355 | G13: =G6*0.355
A14: Depreciation & Amortization | B14: 291.791 | C14: 379.384 | D14: 446.524 | E14: =E6*0.042 | F14: =F6*0.042 | G14: =G6*0.042
A15: Other Operating Expense | B15: 406.485 | C15: 79.511 | D15: 2.735 | E15: 50 | F15: 50 | G15: 50
A16: Total Operating Expenses | B16: =B13+B14+B15 | C16: =C13+C14+C15 | D16: =D13+D14+D15 | E16: =E13+E14+E15 | F16: =F13+F14+F15 | G16: =G13+G14+G15
A18: Operating Income (EBIT) | B18: 1328.408 | C18: 2132.676 | D18: 2505.697 | E18: 2191.72 | F18: 2054.93 | G18: 2198.35
A19: Operating Margin % | B19: 0.164 | C19: 0.222 | D19: 0.237 | E19: 0.199 | F19: 0.178 | G19: 0.18
A21: Other Income/(Expense) | B21: 401.896 | C21: 117.56 | D21: 70.38 | E21: 70 | F21: 70 | G21: 70
A23: Pre-Tax Income (EBT) | B23: 1730.304 | C23: 2250.236 | D23: 2576.077 | E23: =E18+E21 | F23: =F18+F21 | G23: =G18+G21
A24: Income Tax Expense | B24: =B23*0.296 | C24: =C23*0.296 | D24: =D23*0.296 | E24: =E23*0.296 | F24: =F23*0.296 | G24: =G23*0.296
A25: Effective Tax Rate | B25: 0.296 | C25: 0.296 | D25: 0.296 | E25: 0.296 | F25: 0.296 | G25: 0.296
A27: Net Income | B27: 854.8 | C27: 1550.19 | D27: 1814.616 | E27: 1554.16 | F27: 1463.32 | G27: 1561.62
A28: Net Margin % | B28: 0.105 | C28: 0.161 | D28: 0.171 | E28: 0.141 | F28: 0.127 | G28: 0.128
A30: Diluted Shares Outstanding (M) | B30: 128 | C30: 127 | D30: 124 | E30: 119 | F30: 116 | G30: 114
A31: Diluted EPS ($) | B31: 6.68 | C31: 12.2 | D31: 14.64 | E31: 13.05 | F31: 12.64 | G31: 13.72

Sheet Balance Sheet
A1: LULULEMON ATHLETICA INC.
A2: Pro Forma Balance Sheet ($ in millions)
A3: Source: Bloomberg Terminal
B5: FY2023A | C5: FY2024A | D5: FY2025A | E5: FY2026E | F5: FY2027E | G5: FY2028E
A6: ASSETS
A7: Current Assets:
A8: Cash & Cash Equivalents | B8: 1154.867 | C8: 2243.971 | D8: 1984.336 | E8: =G41 | F8: =H41 | G8: =I41
A9: Accounts Receivable | B9: 132.906 | C9: 124.769 | D9: 120.173 | E9: 125.3 | F9: 130.9 | G9: 138.4
A10: Inventory | B10: 1447.367 | C10: 1323.602 | D10: 1442.081 | E10: 1503.7 | F10: 1571.4 | G10: 1660.3
A11: Prepaid & Other Current Assets | B11: 424.313 | C11: 368.235 | D11: 433.712 | E11: 452.2 | F11: 472.6 | G11: 499.3
A12: Total Current Assets | B12: =SUM(B8:B11) | C12: =SUM(C8:C11) | D12: =SUM(D8:D11) | E12: =SUM(E8:E11) | F12: =SUM(F8:F11) | G12: =SUM(G8:G11)
A14: Non-Current Assets:
A15: Net Property, Plant & Equipment | B15: 2239.033 | C15: 2811.421 | D15: 3196.873 | E15: =D15+'Cash Flow Statement'!E16+'Income Statement'!E14 | F15: =E15+'Cash Flow Statement'!F16+'Income Statement'!F14 | G15: =F15+'Cash Flow Statement'!G16+'Income Statement'!G14
A16: Other Non-Current Assets | B16: 208.552 | C16: 219.943 | D16: 426.117 | E16: 430 | F16: 450 | G16: 470
A17: Total Non-Current Assets | B17: =SUM(B15:B16) | C17: =SUM(C15:C16) | D17: =SUM(D15:D16) | E17: =SUM(E15:E16) | F17: =SUM(F15:F16) | G17: =SUM(G15:G16)
A19: TOTAL ASSETS | B19: 5607.038 | C19: 7091.941 | D19: 7603.292 | E19: =E12+E17 | F19: =F12+F17 | G19: =G12+G17
A21: LIABILITIES
A22: Current Liabilities:
A23: Accounts Payable | B23: 172.732 | C23: 348.441 | D23: 271.406 | E23: 283 | F23: 295.7 | G23: 312.5
A24: Accrued & Other Current Liab | B24: 937.273 | C24: 1021.452 | D24: 1109.944 | E24: 1157.3 | F24: 1209.5 | G24: 1277.9
A25: Short-term Borrowings | B25: 207.972 | C25: 249.27 | D25: 275.154 | E25: 290 | F25: 305 | G25: 320
A26: Taxes Payable | B26: 174.221 | C26: 12.098 | D26: 183.126 | E26: 150 | F26: 150 | G26: 150
A27: Total Current Liabilities | B27: 1492.198 | C27: 1631.261 | D27: 1839.63 | E27: =SUM(E23:E26) | F27: =SUM(F23:F26) | G27: =SUM(G23:G26)
A29: Non-Current Liabilities:
A30: Long-term Debt | B30: 862.362 | C30: 1154.012 | D30: 1300.637 | E30: 1350 | F30: 1400 | G30: 1450
A31: Other Non-Current Liabilities | B31: 103.679 | C31: 74.587 | D31: 138.978 | E31: 145 | F31: 150 | G31: 155
A32: Total Non-Current Liabilities | B32: =SUM(B30:B31) | C32: =SUM(C30:C31) | D32: =SUM(D30:D31) | E32: =SUM(E30:E31) | F32: =SUM(F30:F31) | G32: =SUM(G30:G31)
A34: TOTAL LIABILITIES | B34: 2458.239 | C34: 2859.86 | D34: 3279.245 | E34: =E27+E32 | F34: =F27+F32 | G34: =G27+G32
A36: SHAREHOLDERS' EQUITY
A37: Common Stock & APIC | B37: 475.256 | C37: 575.975 | D37: 638.771 | E37: 680 | F37: 720 | G37: 760
A38: Retained Earnings | B38: 2926.127 | C38: 3920.362 | D38: 4109.717 | E38: =D38+'Income Statement'!E27 | F38: =E38+'Income Statement'!F27 | G38: =F38+'Income Statement'!G27
A39: Accum. Other Comprehensive Inc | B39: -252.584 | C39: -264.256 | D39: -424.441 | E39: -450 | F39: -475 | G39: -500
A40: TOTAL SHAREHOLDERS' EQUITY | B40: 3148.799 | C40: 4232.081 | D40: 4324.047 | E40: =SUM(E37:E39) | F40: =SUM(F37:F39) | G40: =SUM(G37:G39)
A42: TOTAL LIABILITIES & EQUITY | B42: =B34+B40 | C42: =C34+C40 | D42: =D34+D40 | E42: =E34+E40 | F42: =F34+F40 | G42: =G34+G40
A44: CHECK: Assets = Liabilities + Equity | B44: =B19-B42 | C44: =C19-C42 | D44: =D19-D42 | E44: =E19-E42 | F44: =F19-F42 | G44: =G19-G42

Sheet Cash Flow Statement
A1: LULULEMON ATHLETICA INC.
A2: Pro Forma Cash Flow Statement ($ in millions)
A3: Source: Bloomberg Terminal
B5: FY2023A | C5: FY2024A | D5: FY2025A | E5: FY2026E | F5: FY2027E | G5: FY2028E
A6: OPERATING ACTIVITIES
A7: Net Income | B7: 854.8 | C7: 1550.19 | D7: 1814.616 | E7: ='Income Statement'!E27 | F7: ='Income Statement'!F27 | G7: ='Income Statement'!G27
A8: Depreciation & Amortization | B8: 291.791 | C8: 379.384 | D8: 446.524 | E8: ='Income Statement'!E14 | F8: ='Income Statement'!F14 | G8: ='Income Statement'!G14
A9: Other Non-Cash Adjustments | B9: 401.326 | C9: 163.852 | D9: 16.252 | E9: 50 | F9: 50 | G9: 50
A10: Changes in Working Capital | B10: -581.454 | C10: 202.738 | D10: -4.679 | E10: -100 | F10: -50 | G10: -75
A11: Net Cash from Operating Activities | B11: 966.463 | C11: 2296.164 | D11: 2272.713 | E11: =SUM(E7:E11) | F11: =SUM(F7:F11) | G11: =SUM(G7:G11)
A13: INVESTING ACTIVITIES
A14: Capital Expenditures | B14: -638.657 | C14: -651.865 | D14: -689.232 | E14: -718.7 | F14: -751 | G14: -793.5
A15: Other Investing Activities | B15: 68.72 | C15: -2.267 | D15: -108.942 | E15: -50 | F15: -50 | G15: -50
A16: Net Cash from Investing Activities | B16: -569.937 | C16: -654.132 | D16: -798.174 | E16: =SUM(E16:E17) | F16: =SUM(F16:F17) | G16: =SUM(G16:G17)
A18: FINANCING ACTIVITIES
A19: Stock Issuance | B19: 11.704 | C19: 42.43 | D19: 19.813 | E19: 25 | F19: 25 | G19: 25
A20: Stock Repurchases | B20: -479.159 | C20: -591.226 | D20: -1672.289 | E20: -800 | F20: -800 | G20: -800
A21: Other Financing Activities | B21: -34.075 | C21: -4.132 | D21: -81.698 | E21: -50 | F21: -50 | G21: -50
A22: Net Cash from Financing Activities | B22: -501.53 | C22: -552.928 | D22: -1734.174 | E22: =SUM(E22:E24) | F22: =SUM(F22:F24) | G22: =SUM(G22:G24)
A24: Net Change in Cash | B24: -105.004 | C24: 1089.104 | D24: -259.635 | E24: =E12+E18+E25 | F24: =F12+F18+F25 | G24: =G12+G18+G25
A25: Beginning Cash Balance | B25: 1259.871 | C25: 1154.867 | D25: 2243.971 | E25: ='Balance Sheet'!D8 | F25: ='Balance Sheet'!E8 | G25: ='Balance Sheet'!F8
A26: Ending Cash Balance | B26: 1154.867 | C26: 2243.971 | D26: 1984.336 | E26: =E27+E28 | F26: =F27+F28 | G26: =G27+G28
A28: Free Cash Flow (CFO - CapEx) | B28: 327.806 | C28: 1644.299 | D28: 1583.481 | E28: =E12-ABS(E16) | F28: =F12-ABS(F16) | G28: =G12-ABS(G16)

Sheet Assumptions & Sources
A1: LULULEMON ATHLETICA - PRO FORMA MODEL
A2: Data Source: Bloomberg Terminal
A5: DATA SOURCE | B5: Bloomberg Macro XIDF (1).xlsm
A6: Date Accessed | B6: February 2026
A8: HISTORICAL DATA (Actuals)
A9: Fiscal Year | B9: Revenue ($M) | C9: Net Income ($M) | D9: Growth Rate
A10: FY 2023 | B10: 8110.5 | C10: 854.8 | D10: 29.6%
A11: FY 2024 | B11: 9619.3 | C11: 1550.2 | D11: 18.6%
A12: FY 2025 | B12: 10588.1 | C12: 1814.6 | D12: 10.1%
A14: CONSENSUS ESTIMATES (Bloomberg)
A15: Fiscal Year | B15: Revenue ($M) | C15: Net Income ($M) | D15: Growth Rate
A16: FY 2026E | B16: 11040.3 | C16: 1554.2 | D16: 4.3%
A17: FY 2027E | B17: 11537.6 | C17: 1463.3 | D17: 4.5%
A18: FY 2028E | B18: 12190.5 | C18: 1561.6 | D18: 5.7%
A20: KEY RATIOS (FY2025)
A21: Gross Margin | B21: 59.2% | C21: Gross Profit / Revenue
A22: Operating Margin | B22: 23.7% | C22: Operating Income / Revenue
A23: Net Margin | B23: 17.1% | C23: Net Income / Revenue
A24: Effective Tax Rate | B24: 29.6% | C24: Income Tax / Pre-Tax Income
A26: ASSUMPTIONS FOR PRO FORMA
A27: Pro forma projections use Bloomberg consensus estimates for revenue and earnings
A28: Balance sheet items projected using historical ratios to revenue
A29: Cash flow derived from income and balance sheet changes
